agere/__init__.py
agere/_version.py
agere/commander/__init__.py
agere/commander/_commander.py
agere/commander/_exceptions.py
agere/commander/_null_logger.py
agere/utils/__init__.py
agere/utils/dispatcher.py
agere/utils/llm_async_converters.py
agere-0.2.0.dist-info/LICENSE
agere-0.2.0.dist-info/METADATA
agere-0.2.0.dist-info/WHEEL
agere-0.2.0.dist-info/top_level.txt
agere-0.2.0.dist-info/RECORD
