Metadata-Version: 2.1
Name: agere
Version: 0.2.0
Summary: The tool is used for building and driving workflows specifically tailored for AI initiatives. It can be used to construct AI agents.
Author-email: Xueao Chao <chaoxueao@gmail.com>
License: MIT License
Project-URL: Homepage, https://github.com/happyapplehorse/agere
Project-URL: Issues, https://github.com/happyapplehorse/agere/issues
Keywords: agents,AI
Classifier: Development Status :: 3 - Alpha
Classifier: Intended Audience :: Developers
Classifier: Topic :: Software Development
Classifier: Topic :: Scientific/Engineering :: Artificial Intelligence
Classifier: Topic :: Software Development :: Libraries
Classifier: Topic :: Software Development :: Libraries :: Python Modules
Classifier: Topic :: Utilities
Classifier: Programming Language :: Python :: 3
Classifier: License :: OSI Approved :: MIT License
Classifier: Operating System :: OS Independent
Requires-Python: >=3.10
License-File: LICENSE
